embedding_explorer/__init__.py
embedding_explorer/app.py
embedding_explorer/assets/favicon.ico
embedding_explorer/blueprints/clustering.py
embedding_explorer/blueprints/dashboard.py
embedding_explorer/blueprints/explorer.py
embedding_explorer/cards.py
embedding_explorer/components/clustering.py
embedding_explorer/components/clustering_settings.py
embedding_explorer/components/model_card.py
embedding_explorer/components/network.py
embedding_explorer/components/plot_settings.py
embedding_explorer/components/slider.py
embedding_explorer/components/word_selector.py
embedding_explorer/plots/network.py
embedding_explorer/prepare/clustering.py
embedding_explorer/prepare/semkern.py
embedding_explorer/prepare/thumbnails.py
embedding_explorer-0.6.0.dist-info/LICENSE
embedding_explorer-0.6.0.dist-info/METADATA
embedding_explorer-0.6.0.dist-info/WHEEL
embedding_explorer-0.6.0.dist-info/RECORD
