Metadata-Version: 2.1
Name: embedding-explorer
Version: 0.6.0
Summary: Tools for interactive visual inspection of semantic embeddings.
License: MIT
Author: Márton Kardos
Author-email: power.up1163@gmail.com
Requires-Python: >=3.8.0
Classifier: License :: OSI Approved :: MIT License
Classifier: Programming Language :: Python :: 3
Classifier: Programming Language :: Python :: 3.8
Classifier: Programming Language :: Python :: 3.9
Classifier: Programming Language :: Python :: 3.10
Classifier: Programming Language :: Python :: 3.11
Classifier: Programming Language :: Python :: 3.12
Requires-Dist: dash (>=2.11.1,<2.12.0)
Requires-Dist: dash-extensions (>=0.1.10,<0.2.0)
Requires-Dist: dash-iconify (>=0.1.2,<0.2.0)
Requires-Dist: dash-mantine-components (>=0.11.1,<0.12.0)
Requires-Dist: hdbscan (>=0.8.30)
Requires-Dist: kaleido (>=0.2.1)
Requires-Dist: neofuzz (>=0.1.2)
Requires-Dist: numpy (>=1.23.0)
Requires-Dist: pandas (>=1.5.2)
Requires-Dist: plotly (>=5.14.0,<5.15.0)
Requires-Dist: scikit-learn (>=1.1.0,<2.0.0)
Requires-Dist: umap-learn (>=0.5.0)
Requires-Dist: wordcloud (>=1.8.2.2,<2.0.0.0)
